simplest_epub_generator/__init__.py
simplest_epub_generator/simplest_epub_generator.py
simplest_epub_generator-0.1.4.dist-info/METADATA
simplest_epub_generator-0.1.4.dist-info/WHEEL
simplest_epub_generator-0.1.4.dist-info/licenses/LICENSE
simplest_epub_generator-0.1.4.dist-info/RECORD
