Metadata-Version: 2.4
Name: simplest_epub_generator
Version: 0.1.4
Summary: A simplest EPUB file generator with image support.
Project-URL: Homepage, https://github.com/rrfedorovich/simplest_epub_generator
Author-email: rrfedorovich <rrfedorovich@gmail.com>
License-File: LICENSE
Classifier: License :: OSI Approved :: MIT License
Classifier: Operating System :: OS Independent
Classifier: Programming Language :: Python :: 3
Requires-Python: >=3.8
Requires-Dist: ebooklib>=0.20
Requires-Dist: lxml>=6.0.2
Requires-Dist: six>=1.17.0
